Workbook

Sheet CorST
A1: Слово | B1: Частота-CorST | C1: IPM-CorST | D1: Ранг-CorST | E1: Номер строки, на которой слово стоит в RLC | F1: IPM-RLC
A2: в | B2: 35889 | C2: 11520.564 | D2: 1 | E2: =MATCH(A2 , RLC!A:A , 0) -> 3 | F2: {=INDEX(RLC!C:C ,E2 , )} -> 37993.234
A3: и | B3: 31435 | C3: 10090.806 | D3: =D2 + 1 -> 2 | E3: =MATCH(A3 , RLC!A:A , 0) -> 2 | F3: {=INDEX(RLC!C:C ,E3 , )} -> 38334.702
A4: на | B4: 13212 | C4: 4241.1239 | D4: =D3 + 1 -> 3 | E4: =MATCH(A4 , RLC!A:A , 0) -> 5 | F4: {=INDEX(RLC!C:C ,E4 , )} -> 13265.412
A5: не | B5: 11811 | C5: 3791.3953 | D5: =D4 + 1 -> 4 | E5: =MATCH(A5 , RLC!A:A , 0) -> 6 | F5: {=INDEX(RLC!C:C ,E5 , )} -> 12860.168
A6: с | B6: 11363 | C6: 3647.5848 | D6: =D5 + 1 -> 5 | E6: =MATCH(A6 , RLC!A:A , 0) -> 8 | F6: {=INDEX(RLC!C:C ,E6 , )} -> 9178.432
A7: что | B7: 10265 | C7: 3295.1208 | D7: =D6 + 1 -> 6 | E7: =MATCH(A7 , RLC!A:A , 0) -> 4 | F7: {=INDEX(RLC!C:C ,E7 , )} -> 16305.402
A8: как | B8: 7396 | C8: 2374.1562 | D8: =D7 + 1 -> 7 | E8: =MATCH(A8 , RLC!A:A , 0) -> 9 | F8: {=INDEX(RLC!C:C ,E8 , )} -> 8273.6097
A9: к | B9: 6790 | C9: 2179.6269 | D9: =D8 + 1 -> 8 | E9: =MATCH(A9 , RLC!A:A , 0) -> 15 | F9: {=INDEX(RLC!C:C ,E9 , )} -> 4742.0127
A10: а | B10: 5924 | C10: 1901.6362 | D10: =D9 + 1 -> 9 | E10: =MATCH(A10 , RLC!A:A , 0) -> 20 | F10: {=INDEX(RLC!C:C ,E10 , )} -> 3449.2197
A11: для | B11: 5652 | C11: 1814.3227 | D11: =D10 + 1 -> 10 | E11: =MATCH(A11 , RLC!A:A , 0) -> 14 | F11: {=INDEX(RLC!C:C ,E11 , )} -> 5009.0748
A12: по | B12: 5634 | C12: 1808.5447 | D12: =D11 + 1 -> 11 | E12: =MATCH(A12 , RLC!A:A , 0) -> 16 | F12: {=INDEX(RLC!C:C ,E12 , )} -> 4641.034
A13: о | B13: 4912 | C13: 1576.7787 | D13: =D12 + 1 -> 12 | E13: =MATCH(A13 , RLC!A:A , 0) -> 13 | F13: {=INDEX(RLC!C:C ,E13 , )} -> 5022.3615
A14: из | B14: 4365 | C14: 1401.1887 | D14: =D13 + 1 -> 13 | E14: =MATCH(A14 , RLC!A:A , 0) -> 17 | F14: {=INDEX(RLC!C:C ,E14 , )} -> 4432.4333
... A1349: форм | B1349: 92 | C1349: 29.532501 | D1349: =D1348 + 1 -> 1348 | E1349: =MATCH(A1349 , RLC!A:A , 0) -> 5289 | F1349: {=INDEX(RLC!C:C ,E1349 , )} -> 21.258673
A1350: школе | B1350: 92 | C1350: 29.532501 | D1350: =D1349 + 1 -> 1349 | E1350: =MATCH(A1350 , RLC!A:A , 0) -> 404 | F1350: {=INDEX(RLC!C:C ,E1350 , )} -> 259.09008 | G1350: =C1350>E1350 -> FALSE
A1351: элементов | B1351: 92 | C1351: 29.532501 | D1351: =D1350 + 1 -> 1350 | E1351: =MATCH(A1351 , RLC!A:A , 0) -> 4112 | F1351: {=INDEX(RLC!C:C ,E1351 , )} -> 27.902008
A1352: этими | B1352: 92 | C1352: 29.532501 | D1352: =D1351 + 1 -> 1351 | E1352: =MATCH(A1352 , RLC!A:A , 0) -> 1492 | F1352: {=INDEX(RLC!C:C ,E1352 , )} -> 77.062689
A1353: артикля | B1353: 91 | C1353: 29.211495 | D1353: =D1352 + 1 -> 1352 | E1353: =MATCH(A1353 , RLC!A:A , 0) -> #N/A | F1353: {=INDEX(RLC!C:C ,E1353 , )} -> #N/A
A1354: всему | B1354: 91 | C1354: 29.211495 | D1354: =D1353 + 1 -> 1353 | E1354: =MATCH(A1354 , RLC!A:A , 0) -> 741 | F1354: {=INDEX(RLC!C:C ,E1354 , )} -> 144.82471
A1355: выполнения | B1355: 91 | C1355: 29.211495 | D1355: =D1354 + 1 -> 1354 | E1355: =MATCH(A1355 , RLC!A:A , 0) -> #N/A | F1355: {=INDEX(RLC!C:C ,E1355 , )} -> #N/A
A1356: достоевский | B1356: 91 | C1356: 29.211495 | D1356: =D1355 + 1 -> 1355 | E1356: =MATCH(A1356 , RLC!A:A , 0) -> #N/A | F1356: {=INDEX(RLC!C:C ,E1356 , )} -> #N/A
A1357: менеджмента | B1357: 91 | C1357: 29.211495 | D1357: =D1356 + 1 -> 1356 | E1357: =MATCH(A1357 , RLC!A:A , 0) -> 2858 | F1357: {=INDEX(RLC!C:C ,E1357 , )} -> 39.860012
A1358: наша | B1358: 91 | C1358: 29.211495 | D1358: =D1357 + 1 -> 1357 | E1358: =MATCH(A1358 , RLC!A:A , 0) -> 551 | F1358: {=INDEX(RLC!C:C ,E1358 , )} -> 193.98539
A1359: поднятая | B1359: 91 | C1359: 29.211495 | D1359: =D1358 + 1 -> 1358 | E1359: =MATCH(A1359 , RLC!A:A , 0) -> #N/A | F1359: {=INDEX(RLC!C:C ,E1359 , )} -> #N/A
A1360: постепенно | B1360: 91 | C1360: 29.211495 | D1360: =D1359 + 1 -> 1359 | E1360: =MATCH(A1360 , RLC!A:A , 0) -> 2469 | F1360: {=INDEX(RLC!C:C ,E1360 , )} -> 46.503347
A1361: рублей | B1361: 91 | C1361: 29.211495 | D1361: =D1360 + 1 -> 1360 | E1361: =MATCH(A1361 , RLC!A:A , 0) -> 1697 | F1361: {=INDEX(RLC!C:C ,E1361 , )} -> 67.76202
A1362: сегодняшний | B1362: 91 | C1362: 29.211495 | D1362: =D1361 + 1 -> 1361 | E1362: =MATCH(A1362 , RLC!A:A , 0) -> 1873 | F1362: {=INDEX(RLC!C:C ,E1362 , )} -> 62.447352
... A1716: чехов | B1716: 73 | C1716: 23.433397 | D1716: =D1715 + 1 -> 1715 | E1716: =MATCH(A1716 , RLC!A:A , 0) -> #N/A | F1716: {=INDEX(RLC!C:C ,E1716 , )} -> #N/A
A1717: шапочка | B1717: 73 | C1717: 23.433397 | D1717: =D1716 + 1 -> 1716 | E1717: =MATCH(A1717 , RLC!A:A , 0) -> 3340 | F1717: {=INDEX(RLC!C:C ,E1717 , )} -> 34.545343 | G1717: =C1717>E1717 -> FALSE
A1718: широко | B1718: 73 | C1718: 23.433397 | D1718: =D1717 + 1 -> 1717 | E1718: =MATCH(A1718 , RLC!A:A , 0) -> 1585 | F1718: {=INDEX(RLC!C:C ,E1718 , )} -> 73.076688 | G1718: =C1718>E1718 -> FALSE
A1719: эмоций | B1719: 73 | C1719: 23.433397 | D1719: =D1718 + 1 -> 1718 | E1719: =MATCH(A1719 , RLC!A:A , 0) -> 6913 | F1719: {=INDEX(RLC!C:C ,E1719 , )} -> 15.944005
A1720: большие | B1720: 72 | C1720: 23.112392 | D1720: =D1719 + 1 -> 1719 | E1720: =MATCH(A1720 , RLC!A:A , 0) -> 837 | F1720: {=INDEX(RLC!C:C ,E1720 , )} -> 128.8807
A1721: большого | B1721: 72 | C1721: 23.112392 | D1721: =D1720 + 1 -> 1720 | E1721: =MATCH(A1721 , RLC!A:A , 0) -> 2651 | F1721: {=INDEX(RLC!C:C ,E1721 , )} -> 42.517346
A1722: ведет | B1722: 72 | C1722: 23.112392 | D1722: =D1721 + 1 -> 1721 | E1722: =MATCH(A1722 , RLC!A:A , 0) -> 3483 | F1722: {=INDEX(RLC!C:C ,E1722 , )} -> 31.888009
A1723: вниз | B1723: 72 | C1723: 23.112392 | D1723: =D1722 + 1 -> 1722 | E1723: =MATCH(A1723 , RLC!A:A , 0) -> 2832 | F1723: {=INDEX(RLC!C:C ,E1723 , )} -> 39.860012
A1724: вузов | B1724: 72 | C1724: 23.112392 | D1724: =D1723 + 1 -> 1723 | E1724: =MATCH(A1724 , RLC!A:A , 0) -> 6052 | F1724: {=INDEX(RLC!C:C ,E1724 , )} -> 17.272672
A1725: выражений | B1725: 72 | C1725: 23.112392 | D1725: =D1724 + 1 -> 1724 | E1725: =MATCH(A1725 , RLC!A:A , 0) -> 3786 | F1725: {=INDEX(RLC!C:C ,E1725 , )} -> 29.230675
A1726: гражданским | B1726: 72 | C1726: 23.112392 | D1726: =D1725 + 1 -> 1725 | E1726: =MATCH(A1726 , RLC!A:A , 0) -> #N/A | F1726: {=INDEX(RLC!C:C ,E1726 , )} -> #N/A
A1727: изучить | B1727: 72 | C1727: 23.112392 | D1727: =D1726 + 1 -> 1726 | E1727: =MATCH(A1727 , RLC!A:A , 0) -> 4372 | F1727: {=INDEX(RLC!C:C ,E1727 , )} -> 25.244674
A1728: ин | B1728: 72 | C1728: 23.112392 | D1728: =D1727 + 1 -> 1727 | E1728: =MATCH(A1728 , RLC!A:A , 0) -> #N/A | F1728: {=INDEX(RLC!C:C ,E1728 , )} -> #N/A
A1729: интернета | B1729: 72 | C1729: 23.112392 | D1729: =D1728 + 1 -> 1728 | E1729: =MATCH(A1729 , RLC!A:A , 0) -> 2960 | F1729: {=INDEX(RLC!C:C ,E1729 , )} -> 38.531345
A1730: когнитивных | B1730: 72 | C1730: 23.112392 | D1730: =D1729 + 1 -> 1729 | E1730: =MATCH(A1730 , RLC!A:A , 0) -> #N/A | F1730: {=INDEX(RLC!C:C ,E1730 , )} -> #N/A
... A2090: чтение | B2090: 61 | C2090: 19.581332 | D2090: =D2089 + 1 -> 2089 | E2090: =MATCH(A2090 , RLC!A:A , 0) -> 2647 | F2090: {=INDEX(RLC!C:C ,E2090 , )} -> 43.846013
A2091: школы | B2091: 61 | C2091: 19.581332 | D2091: =D2090 + 1 -> 2090 | E2091: =MATCH(A2091 , RLC!A:A , 0) -> 542 | F2091: {=INDEX(RLC!C:C ,E2091 , )} -> 197.97139 | G2091: =C2091>E2091 -> FALSE
A2092: больших | B2092: 60 | C2092: 19.260326 | D2092: =D2091 + 1 -> 2091 | E2092: =MATCH(A2092 , RLC!A:A , 0) -> 1082 | F2092: {=INDEX(RLC!C:C ,E2092 , )} -> 102.30736
A2093: будем | B2093: 60 | C2093: 19.260326 | D2093: =D2092 + 1 -> 2092 | E2093: =MATCH(A2093 , RLC!A:A , 0) -> 1097 | F2093: {=INDEX(RLC!C:C ,E2093 , )} -> 100.9787
A2094: вариативность | B2094: 60 | C2094: 19.260326 | D2094: =D2093 + 1 -> 2093 | E2094: =MATCH(A2094 , RLC!A:A , 0) -> #N/A | F2094: {=INDEX(RLC!C:C ,E2094 , )} -> #N/A
A2095: возмещения | B2095: 60 | C2095: 19.260326 | D2095: =D2094 + 1 -> 2094 | E2095: =MATCH(A2095 , RLC!A:A , 0) -> #N/A | F2095: {=INDEX(RLC!C:C ,E2095 , )} -> #N/A
A2096: возможностей | B2096: 60 | C2096: 19.260326 | D2096: =D2095 + 1 -> 2095 | E2096: =MATCH(A2096 , RLC!A:A , 0) -> 2835 | F2096: {=INDEX(RLC!C:C ,E2096 , )} -> 39.860012
A2097: выяснить | B2097: 60 | C2097: 19.260326 | D2097: =D2096 + 1 -> 2096 | E2097: =MATCH(A2097 , RLC!A:A , 0) -> 7547 | F2097: {=INDEX(RLC!C:C ,E2097 , )} -> 13.286671
A2098: гипотез | B2098: 60 | C2098: 19.260326 | D2098: =D2097 + 1 -> 2097 | E2098: =MATCH(A2098 , RLC!A:A , 0) -> #N/A | F2098: {=INDEX(RLC!C:C ,E2098 , )} -> #N/A
A2099: голове | B2099: 60 | C2099: 19.260326 | D2099: =D2098 + 1 -> 2098 | E2099: =MATCH(A2099 , RLC!A:A , 0) -> 2131 | F2099: {=INDEX(RLC!C:C ,E2099 , )} -> 53.146682
A2100: гражданском | B2100: 60 | C2100: 19.260326 | D2100: =D2099 + 1 -> 2099 | E2100: =MATCH(A2100 , RLC!A:A , 0) -> #N/A | F2100: {=INDEX(RLC!C:C ,E2100 , )} -> #N/A
A2101: дается | B2101: 60 | C2101: 19.260326 | D2101: =D2100 + 1 -> 2100 | E2101: =MATCH(A2101 , RLC!A:A , 0) -> 4145 | F2101: {=INDEX(RLC!C:C ,E2101 , )} -> 26.573341
A2102: дальнейшего | B2102: 60 | C2102: 19.260326 | D2102: =D2101 + 1 -> 2101 | E2102: =MATCH(A2102 , RLC!A:A , 0) -> #N/A | F2102: {=INDEX(RLC!C:C ,E2102 , )} -> #N/A
A2103: другая | B2103: 60 | C2103: 19.260326 | D2103: =D2102 + 1 -> 2102 | E2103: =MATCH(A2103 , RLC!A:A , 0) -> 1157 | F2103: {=INDEX(RLC!C:C ,E2103 , )} -> 96.992695
... A2510: фоне | B2510: 50 | C2510: 16.050272 | D2510: =D2509 + 1 -> 2509 | E2510: =MATCH(A2510 , RLC!A:A , 0) -> #N/A | F2510: {=INDEX(RLC!C:C ,E2510 , )} -> #N/A
A2511: широкий | B2511: 50 | C2511: 16.050272 | D2511: =D2510 + 1 -> 2510 | E2511: =MATCH(A2511 , RLC!A:A , 0) -> 6907 | F2511: {=INDEX(RLC!C:C ,E2511 , )} -> 15.944005 | G2511: =C2511>E2511 -> FALSE
A2512: адресован | B2512: 49 | C2512: 15.729267 | D2512: =D2511 + 1 -> 2511 | E2512: =MATCH(A2512 , RLC!A:A , 0) -> #N/A | F2512: {=INDEX(RLC!C:C ,E2512 , )} -> #N/A
A2513: база | B2513: 49 | C2513: 15.729267 | D2513: =D2512 + 1 -> 2512 | E2513: =MATCH(A2513 , RLC!A:A , 0) -> #N/A | F2513: {=INDEX(RLC!C:C ,E2513 , )} -> #N/A
A2514: вариативности | B2514: 49 | C2514: 15.729267 | D2514: =D2513 + 1 -> 2513 | E2514: =MATCH(A2514 , RLC!A:A , 0) -> #N/A | F2514: {=INDEX(RLC!C:C ,E2514 , )} -> #N/A
A2515: введения | B2515: 49 | C2515: 15.729267 | D2515: =D2514 + 1 -> 2514 | E2515: =MATCH(A2515 , RLC!A:A , 0) -> 7509 | F2515: {=INDEX(RLC!C:C ,E2515 , )} -> 13.286671
A2516: видел | B2516: 49 | C2516: 15.729267 | D2516: =D2515 + 1 -> 2515 | E2516: =MATCH(A2516 , RLC!A:A , 0) -> 1926 | F2516: {=INDEX(RLC!C:C ,E2516 , )} -> 59.790017
A2517: высокий | B2517: 49 | C2517: 15.729267 | D2517: =D2516 + 1 -> 2516 | E2517: =MATCH(A2517 , RLC!A:A , 0) -> 2129 | F2517: {=INDEX(RLC!C:C ,E2517 , )} -> 53.146682
A2518: выходит | B2518: 49 | C2518: 15.729267 | D2518: =D2517 + 1 -> 2517 | E2518: =MATCH(A2518 , RLC!A:A , 0) -> 3637 | F2518: {=INDEX(RLC!C:C ,E2518 , )} -> 30.559342
A2519: герои | B2519: 49 | C2519: 15.729267 | D2519: =D2518 + 1 -> 2518 | E2519: =MATCH(A2519 , RLC!A:A , 0) -> 2502 | F2519: {=INDEX(RLC!C:C ,E2519 , )} -> 45.17468
A2520: глагольных | B2520: 49 | C2520: 15.729267 | D2520: =D2519 + 1 -> 2519 | E2520: =MATCH(A2520 , RLC!A:A , 0) -> #N/A | F2520: {=INDEX(RLC!C:C ,E2520 , )} -> #N/A
A2521: гпк | B2521: 49 | C2521: 15.729267 | D2521: =D2520 + 1 -> 2520 | E2521: =MATCH(A2521 , RLC!A:A , 0) -> #N/A | F2521: {=INDEX(RLC!C:C ,E2521 , )} -> #N/A
A2522: егэ | B2522: 49 | C2522: 15.729267 | D2522: =D2521 + 1 -> 2521 | E2522: =MATCH(A2522 , RLC!A:A , 0) -> 3049 | F2522: {=INDEX(RLC!C:C ,E2522 , )} -> 37.202678
A2523: единственный | B2523: 49 | C2523: 15.729267 | D2523: =D2522 + 1 -> 2522 | E2523: =MATCH(A2523 , RLC!A:A , 0) -> 1892 | F2523: {=INDEX(RLC!C:C ,E2523 , )} -> 61.118685
... A2664: человеке | B2664: 47 | C2664: 15.087256 | D2664: =D2663 + 1 -> 2663 | E2664: =MATCH(A2664 , RLC!A:A , 0) -> 2556 | F2664: {=INDEX(RLC!C:C ,E2664 , )} -> 45.17468
A2665: шаг | B2665: 47 | C2665: 15.087256 | D2665: =D2664 + 1 -> 2664 | E2665: =MATCH(A2665 , RLC!A:A , 0) -> 2738 | F2665: {=INDEX(RLC!C:C ,E2665 , )} -> 42.517346 | G2665: =C2665>E2665 -> FALSE
A2666: авторских | B2666: 46 | C2666: 14.76625 | D2666: =D2665 + 1 -> 2665 | E2666: =MATCH(A2666 , RLC!A:A , 0) -> #N/A | F2666: {=INDEX(RLC!C:C ,E2666 , )} -> #N/A
A2667: будь | B2667: 46 | C2667: 14.76625 | D2667: =D2666 + 1 -> 2666 | E2667: =MATCH(A2667 , RLC!A:A , 0) -> 3245 | F2667: {=INDEX(RLC!C:C ,E2667 , )} -> 34.545343
A2668: бытия | B2668: 46 | C2668: 14.76625 | D2668: =D2667 + 1 -> 2667 | E2668: =MATCH(A2668 , RLC!A:A , 0) -> #N/A | F2668: {=INDEX(RLC!C:C ,E2668 , )} -> #N/A
A2669: вводит | B2669: 46 | C2669: 14.76625 | D2669: =D2668 + 1 -> 2668 | E2669: =MATCH(A2669 , RLC!A:A , 0) -> #N/A | F2669: {=INDEX(RLC!C:C ,E2669 , )} -> #N/A
A2670: вещь | B2670: 46 | C2670: 14.76625 | D2670: =D2669 + 1 -> 2669 | E2670: =MATCH(A2670 , RLC!A:A , 0) -> 2655 | F2670: {=INDEX(RLC!C:C ,E2670 , )} -> 42.517346
A2671: взаимодействии | B2671: 46 | C2671: 14.76625 | D2671: =D2670 + 1 -> 2670 | E2671: =MATCH(A2671 , RLC!A:A , 0) -> #N/A | F2671: {=INDEX(RLC!C:C ,E2671 , )} -> #N/A
A2672: выборки | B2672: 46 | C2672: 14.76625 | D2672: =D2671 + 1 -> 2671 | E2672: =MATCH(A2672 , RLC!A:A , 0) -> #N/A | F2672: {=INDEX(RLC!C:C ,E2672 , )} -> #N/A
A2673: выделены | B2673: 46 | C2673: 14.76625 | D2673: =D2672 + 1 -> 2672 | E2673: =MATCH(A2673 , RLC!A:A , 0) -> #N/A | F2673: {=INDEX(RLC!C:C ,E2673 , )} -> #N/A
A2674: гипотезу | B2674: 46 | C2674: 14.76625 | D2674: =D2673 + 1 -> 2673 | E2674: =MATCH(A2674 , RLC!A:A , 0) -> #N/A | F2674: {=INDEX(RLC!C:C ,E2674 , )} -> #N/A
A2675: государств | B2675: 46 | C2675: 14.76625 | D2675: =D2674 + 1 -> 2674 | E2675: =MATCH(A2675 , RLC!A:A , 0) -> 991 | F2675: {=INDEX(RLC!C:C ,E2675 , )} -> 111.60803
A2676: доме | B2676: 46 | C2676: 14.76625 | D2676: =D2675 + 1 -> 2675 | E2676: =MATCH(A2676 , RLC!A:A , 0) -> 907 | F2676: {=INDEX(RLC!C:C ,E2676 , )} -> 120.9087
A2677: думать | B2677: 46 | C2677: 14.76625 | D2677: =D2676 + 1 -> 2676 | E2677: =MATCH(A2677 , RLC!A:A , 0) -> 720 | F2677: {=INDEX(RLC!C:C ,E2677 , )} -> 147.48204
... A2830: ценностей | B2830: 44 | C2830: 14.124239 | D2830: =D2829 + 1 -> 2829 | E2830: =MATCH(A2830 , RLC!A:A , 0) -> 1925 | F2830: {=INDEX(RLC!C:C ,E2830 , )} -> 61.118685
A2831: широкого | B2831: 44 | C2831: 14.124239 | D2831: =D2830 + 1 -> 2830 | E2831: =MATCH(A2831 , RLC!A:A , 0) -> 5302 | F2831: {=INDEX(RLC!C:C ,E2831 , )} -> 21.258673 | G2831: =C2831>E2831 -> FALSE
A2832: широкой | B2832: 44 | C2832: 14.124239 | D2832: =D2831 + 1 -> 2831 | E2832: =MATCH(A2832 , RLC!A:A , 0) -> 1998 | F2832: {=INDEX(RLC!C:C ,E2832 , )} -> 58.46135 | G2832: =C2832>E2832 -> FALSE
A2833: экономиста | B2833: 44 | C2833: 14.124239 | D2833: =D2832 + 1 -> 2832 | E2833: =MATCH(A2833 , RLC!A:A , 0) -> #N/A | F2833: {=INDEX(RLC!C:C ,E2833 , )} -> #N/A
A2834: экономического | B2834: 44 | C2834: 14.124239 | D2834: =D2833 + 1 -> 2833 | E2834: =MATCH(A2834 , RLC!A:A , 0) -> 917 | F2834: {=INDEX(RLC!C:C ,E2834 , )} -> 120.9087
A2835: эксперта | B2835: 44 | C2835: 14.124239 | D2835: =D2834 + 1 -> 2834 | E2835: =MATCH(A2835 , RLC!A:A , 0) -> #N/A | F2835: {=INDEX(RLC!C:C ,E2835 , )} -> #N/A
A2836: января | B2836: 44 | C2836: 14.124239 | D2836: =D2835 + 1 -> 2835 | E2836: =MATCH(A2836 , RLC!A:A , 0) -> 1413 | F2836: {=INDEX(RLC!C:C ,E2836 , )} -> 81.04869
A2837: абстрактное | B2837: 43 | C2837: 13.803234 | D2837: =D2836 + 1 -> 2836 | E2837: =MATCH(A2837 , RLC!A:A , 0) -> #N/A | F2837: {=INDEX(RLC!C:C ,E2837 , )} -> #N/A
A2838: автору | B2838: 43 | C2838: 13.803234 | D2838: =D2837 + 1 -> 2837 | E2838: =MATCH(A2838 , RLC!A:A , 0) -> 6004 | F2838: {=INDEX(RLC!C:C ,E2838 , )} -> 17.272672
A2839: включая | B2839: 43 | C2839: 13.803234 | D2839: =D2838 + 1 -> 2838 | E2839: =MATCH(A2839 , RLC!A:A , 0) -> 1415 | F2839: {=INDEX(RLC!C:C ,E2839 , )} -> 79.720023
A2840: встретить | B2840: 43 | C2840: 13.803234 | D2840: =D2839 + 1 -> 2839 | E2840: =MATCH(A2840 , RLC!A:A , 0) -> 4555 | F2840: {=INDEX(RLC!C:C ,E2840 , )} -> 23.916007
A2841: выяснилось | B2841: 43 | C2841: 13.803234 | D2841: =D2840 + 1 -> 2840 | E2841: =MATCH(A2841 , RLC!A:A , 0) -> 6485 | F2841: {=INDEX(RLC!C:C ,E2841 , )} -> 15.944005
A2842: грамматика | B2842: 43 | C2842: 13.803234 | D2842: =D2841 + 1 -> 2841 | E2842: =MATCH(A2842 , RLC!A:A , 0) -> 6065 | F2842: {=INDEX(RLC!C:C ,E2842 , )} -> 17.272672
A2843: движений | B2843: 43 | C2843: 13.803234 | D2843: =D2842 + 1 -> 2842 | E2843: =MATCH(A2843 , RLC!A:A , 0) -> 4347 | F2843: {=INDEX(RLC!C:C ,E2843 , )} -> 25.244674
A2844: доказывает | B2844: 43 | C2844: 13.803234 | D2844: =D2843 + 1 -> 2843 | E2844: =MATCH(A2844 , RLC!A:A , 0) -> 2364 | F2844: {=INDEX(RLC!C:C ,E2844 , )} -> 47.832014
...

Sheet RLC
A1: Слово | B1: Частота-RLC | C1: IPM-RLC | D1: Ранг-RLC | E1: Номер строки, на которой слово стоит в CorST
A2: и | B2: 28852 | C2: 38334.702 | D2: 1 | E2: =MATCH(A2 , CorST!A:A , 0) -> 3
A3: в | B3: 28595 | C3: 37993.234 | D3: =D2 + 1 -> 2 | E3: =MATCH(A3 , CorST!A:A , 0) -> 2
A4: что | B4: 12272 | C4: 16305.402 | D4: =D3 + 1 -> 3 | E4: =MATCH(A4 , CorST!A:A , 0) -> 7
A5: на | B5: 9984 | C5: 13265.412 | D5: =D4 + 1 -> 4 | E5: =MATCH(A5 , CorST!A:A , 0) -> 4
A6: не | B6: 9679 | C6: 12860.168 | D6: =D5 + 1 -> 5 | E6: =MATCH(A6 , CorST!A:A , 0) -> 5
A7: я | B7: 8489 | C7: 11279.055 | D7: =D6 + 1 -> 6 | E7: =MATCH(A7 , CorST!A:A , 0) -> 24
A8: с | B8: 6908 | C8: 9178.432 | D8: =D7 + 1 -> 7 | E8: =MATCH(A8 , CorST!A:A , 0) -> 6
A9: как | B9: 6227 | C9: 8273.6097 | D9: =D8 + 1 -> 8 | E9: =MATCH(A9 , CorST!A:A , 0) -> 8
A10: это | B10: 5389 | C10: 7160.1868 | D10: =D9 + 1 -> 9 | E10: =MATCH(A10 , CorST!A:A , 0) -> 15
A11: но | B11: 4307 | C11: 5722.569 | D11: =D10 + 1 -> 10 | E11: =MATCH(A11 , CorST!A:A , 0) -> 19
A12: он | B12: 4050 | C12: 5381.1016 | D12: =D11 + 1 -> 11 | E12: =MATCH(A12 , CorST!A:A , 0) -> 21
A13: о | B13: 3780 | C13: 5022.3615 | D13: =D12 + 1 -> 12 | E13: =MATCH(A13 , CorST!A:A , 0) -> 13
A14: для | B14: 3770 | C14: 5009.0748 | D14: =D13 + 1 -> 13 | E14: =MATCH(A14 , CorST!A:A , 0) -> 11
... A8127: японский | B8127: 10 | C8127: 13.286671 | D8127: =D8126 + 1 -> 8126 | E8127: =MATCH(A8127 , CorST!A:A , 0) -> 14067

Sheet merge
A1: Слово | B1: IPM-CorST | C1: IPM-RLC
A2: ячейки | B2: 11520.564 | C2: 37993.234
A3: ячеек | B3: 10090.806 | C3: 38334.702
A4: ясным | B4: 4241.1239 | C4: 13265.412
A5: ясность | B5: 3791.3953 | C5: 12860.168
A6: ясности | B6: 3647.5848 | C6: 9178.432
A7: ясно | B7: 3295.1208 | C7: 16305.402
A8: ясна | B8: 2374.1562 | C8: 8273.6097
A9: яркость | B9: 2179.6269 | C9: 4742.0127
A10: яркости | B10: 1901.6362 | C10: 3449.2197
A11: яркой | B11: 1814.3227 | C11: 5009.0748
A12: яркое | B12: 1808.5447 | C12: 4641.034
A13: ярко | B13: 1576.7787 | C13: 5022.3615
... A61: являться | B61: 349.57492 | C61: 482.30614
A62: являлся | B62: 347.9699
A63: являлось | B63: 345.40185 | C63: 987.19962
A64: являлись | B64: 343.47582 | C64: 180.69872
A65: являлась | B65: 343.47582 | C65: 196.64272
A66: является | B66: 340.90778 | C66: 1162.5837
A67: явлениями | B67: 340.90778 | C67: 749.36822
A68: явлениям | B68: 337.05571 | C68: 1194.4717
A69: явления | B69: 334.80867 | C69: 528.80949
A70: явлению | B70: 332.56164 | C70: 1353.9117
A71: явлений | B71: 332.24063 | C71: 3013.4169
A72: явлении | B72: 323.89449 | C72: 976.57029
A73: явлением | B73: 321.96846 | C73: 1037.689
A74: явление | B74: 321.64745 | C74: 1195.8003
... A114: эффектов | B114: 218.6047 | C114: 1909.2946
A115: эффективных | B115: 215.07365
A116: эффективным | B116: 213.14761 | C116: 310.90809
A117: эффективный | B117: 211.86359 | C117: 132.86671
A118: эффективность | B118: 211.54259 | C118: 1567.8271
A119: эффективности | B119: 209.29555 | C119: 389.29945
A120: эффективно | B120: 208.97454 | C120: 1307.4084
A121: эффективнее | B121: 207.36951 | C121: 572.6555
A122: эффективен | B122: 204.48047 | C122: 70.419354
A123: эффекта | B123: 203.19644 | C123: 1792.3719
A124: эффект | B124: 203.19644 | C124: 615.17285
A125: эту | B125: 202.55443 | C125: 2012.9306
A126: этот | B126: 202.23343 | C126: 659.01886
A127: этос | B127: 200.94941 | C127: 718.80888
... A142: этапов | B142: 188.7512 | C142: 495.59281
A143: этапе | B143: 188.7512
A144: этапах | B144: 187.78818 | C144: 1020.4163
A145: этапа | B145: 187.46718 | C145: 1058.9476
A146: этап | B146: 186.82517 | C146: 328.18076
A147: этажей | B147: 186.82517 | C147: 54.475349
A148: этаже | B148: 186.18316 | C148: 312.23676
A149: эта | B149: 186.18316 | C149: 15.944005
A150: эссе | B150: 185.86215
A151: эры | B151: 185.86215 | C151: 107.62203
A152: эра | B152: 184.57813 | C152: 551.39683
A153: эпоху | B153: 182.6521 | C153: 447.7608
A154: эпохи | B154: 179.44204 | C154: 398.60012
A155: эпоха | B155: 178.47902 | C155: 320.20876
A156: эпишура | B156: 178.47902 | C156: 644.40352
A157: эпизоды | B157: 178.15802 | C157: 904.82226
A158: эпизод | B158: 177.83701 | C158: 559.36883
A159: энциклопедия | B159: 177.83701 | C159: 503.56481
A160: энциклопедический | B160: 177.51601 | C160: 511.53682
A161: энциклопедии | B161: 175.91098 | C161: 47.832014
A162: энергия | B162: 175.58998 | C162: 46.503347
... A225: эксперт | B225: 133.53826 | C225: 361.39744
A226: эксперименты | B226: 132.57525
A227: экспериментов | B227: 131.93324 | C227: 652.37552
A228: эксперименте | B228: 131.29123 | C228: 220.55873
A229: экспериментах | B229: 130.97022 | C229: 208.60073
A230: экспериментальные | B230: 130.64921 | C230: 519.50882
A231: экспериментально | B231: 130.0072 | C231: 458.39013
A232: эксперимента | B232: 129.6862 | C232: 263.07608
A233: эксперимент | B233: 129.6862 | C233: 597.90017
A234: экспериенцером | B234: 129.36519 | C234: 53.146682
A235: экспериенцера | B235: 128.72318 | C235: 320.20876
A236: экспериенцер | B236: 128.40218 | C236: 382.65611
A237: экскурсию | B237: 128.08117 | C237: 309.57942
A238: экскурсии | B238: 127.43916 | C238: 704.19354
... A260: экономистов | B260: 118.77201 | C260: 382.65611
A261: экономистам | B261: 118.13 | C261: IPM-RLC
A262: экономиста | B262: 118.13 | C262: 422.51612
A263: экономист | B263: 117.48799 | C263: 73.076688
A264: экономику | B264: 117.48799 | C264: 143.49604
A265: экономикой | B265: 117.48799 | C265: 500.90748
A266: экономики | B266: 116.52497 | C266: 333.49543
A267: экономике | B267: 116.52497 | C267: 754.68289
A268: экономика | B268: 115.88296 | C268: 203.28606
A269: экономии | B269: 115.88296 | C269: 304.26476
A270: экологов | B270: 115.56196 | C270: 342.7961
A271: экологическую | B271: 115.56196 | C271: 470.34814
A272: экологической | B272: 115.24095 | C272: 167.41205
A273: экологического | B273: 113.63593 | C273: 566.01217
... A298: шутите | B298: 106.89481 | C298: 45.17468
A299: шум | B299: 106.2528
A300: штатов | B300: 105.9318 | C300: 358.7401
A301: штате | B301: 105.61079 | C301: 152.79671
A302: штатах | B302: 105.28978 | C302: 213.9154
A303: штата | B303: 104.96878 | C303: 150.13938
A304: штат | B304: 104.64777 | C304: 13.286671
A305: шт | B305: 104.64777 | C305: 197.97139
A306: шрифтом | B306: 104.32677 | C306: 866.29092
A307: шоу | B307: 104.32677 | C307: 217.9014
...
